gdt/__init__.py
gdt/cli.py
gdt/gdict.py
gdt/gff3_utils.py
gdt/log_setup.py
gdt/py.typed
gdt-1.1.3.dist-info/licenses/LICENSE
gdt-1.1.3.dist-info/METADATA
gdt-1.1.3.dist-info/WHEEL
gdt-1.1.3.dist-info/entry_points.txt
gdt-1.1.3.dist-info/top_level.txt
gdt-1.1.3.dist-info/RECORD
