Metadata-Version: 2.4
Name: gdt
Version: 1.1.3
Summary: Gene Dictionary Tool - Bioinformatics package
Author-email: Breno Dupin <breno.dupin@gmail.com>, Matheus Sanita Lima <msanital@uwo.ca>
License-Expression: MIT
Project-URL: Homepage, https://github.com/brenodupin/gdt
Project-URL: Source, https://github.com/brenodupin/gdt
Keywords: bioinformatics,genomics,gene-analysis,computational-biology
Classifier: Development Status :: 4 - Beta
Classifier: Intended Audience :: Developers
Classifier: Intended Audience :: Science/Research
Classifier: Topic :: Scientific/Engineering
Classifier: Topic :: Scientific/Engineering :: Bio-Informatics
Classifier: Topic :: Software Development :: Libraries :: Python Modules
Classifier: Programming Language :: Python :: 3
Classifier: Programming Language :: Python :: 3.10
Classifier: Programming Language :: Python :: 3.11
Classifier: Programming Language :: Python :: 3.12
Classifier: Programming Language :: Python :: 3.13
Classifier: Operating System :: POSIX :: Linux
Classifier: Operating System :: MacOS
Requires-Python: >=3.12
License-File: LICENSE
Requires-Dist: pandas<3.0.0,>=1.5.3
Dynamic: license-file
